{ "height":25,
 "layers":[
        {
         "data":[3, 3, 3, 3, 3, 3, 3, 3, 3, 3, 3, 3, 3, 3, 3, 3, 3, 3, 3, 3, 3, 3, 3, 3, 3, 3, 5, 5, 5, 6, 5, 3, 6, 5, 5, 5, 5, 5, 6, 5, 2, 5, 5, 5, 5, 5, 5, 6, 5, 3, 3, 5, 5, 5, 5, 5, 3, 5, 5, 5, 5, 5, 5, 5, 5, 2, 5, 5, 5, 5, 5, 5, 5, 5, 3, 3, 3, 3, 3, 3, 3, 3, 5, 5, 5, 5, 5, 5, 5, 5, 2, 5, 5, 5, 5, 5, 5, 5, 5, 3, 3, 6, 5, 5, 5, 5, 2, 5, 5, 5, 5, 5, 5, 5, 5, 2, 5, 5, 5, 5, 5, 5, 5, 5, 3, 3, 5, 5, 5, 5, 5, 2, 5, 5, 5, 5, 5, 5, 5, 5, 2, 5, 5, 5, 5, 5, 5, 5, 5, 3, 3, 5, 5, 5, 5, 5, 2, 5, 5, 5, 5, 5, 5, 5, 5, 2, 5, 5, 5, 5, 5, 5, 5, 5, 3, 3, 5, 5, 5, 5, 5, 2, 5, 5, 5, 5, 5, 5, 5, 5, 2, 5, 5, 5, 5, 5, 5, 5, 5, 3, 3, 5, 5, 5, 5, 5, 2, 5, 5, 5, 5, 5, 5, 5, 5, 2, 5, 5, 5, 5, 5, 5, 5, 5, 3, 3, 5, 5, 5, 5, 5, 2, 5, 5, 5, 5, 5, 5, 5, 5, 2, 5, 5, 5, 5, 5, 5, 5, 5, 3, 3, 5, 5, 5, 5, 5, 2, 5, 5, 5, 5, 5, 5, 5, 5, 2, 5, 5, 5, 5, 5, 5, 5, 5, 3, 3, 5, 5, 6, 5, 5, 2, 5, 5, 5, 5, 5, 5, 5, 5, 2, 5, 5, 5, 5, 5, 5, 5, 5, 3, 3, 5, 5, 5, 5, 5, 2, 5, 5, 5, 5, 5, 5, 5, 5, 2, 6, 5, 5, 5, 5, 5, 5, 5, 3, 3, 2, 2, 2, 2, 2, 2, 2, 2, 2, 2, 2, 2, 2, 3, 3, 3, 3, 3, 3, 3, 3, 3, 3, 3, 3, 5, 5, 5, 5, 5, 5, 5, 5, 5, 5, 5, 5, 2, 6, 5, 5, 5, 5, 5, 3, 5, 5, 5, 3, 3, 5, 5, 5, 5, 5, 5, 5, 5, 5, 5, 5, 5, 2, 5, 5, 5, 5, 5, 5, 5, 5, 5, 5, 3, 3, 5, 5, 5, 5, 5, 5, 5, 5, 5, 5, 5, 5, 2, 5, 5, 5, 5, 3, 5, 5, 5, 5, 5, 3, 3, 5, 5, 5, 5, 5, 5, 5, 5, 5, 5, 5, 5, 2, 5, 5, 5, 5, 5, 5, 5, 5, 5, 3, 3, 3, 5, 5, 5, 5, 5, 6, 5, 5, 5, 5, 5, 5, 2, 5, 5, 3, 5, 5, 5, 5, 5, 5, 5, 3, 3, 5, 5, 5, 5, 5, 5, 5, 5, 5, 5, 5, 5, 2, 5, 5, 5, 5, 5, 5, 5, 3, 5, 5, 3, 3, 5, 5, 5, 5, 5, 5, 5, 5, 5, 5, 5, 5, 2, 2, 5, 5, 5, 5, 5, 5, 5, 5, 5, 3, 3, 5, 5, 5, 5, 5, 5, 5, 5, 5, 5, 5, 5, 2, 5, 5, 5, 5, 5, 3, 5, 5, 5, 5, 3, 3, 5, 5, 5, 5, 5, 5, 5, 5, 5, 5, 5, 5, 2, 5, 5, 5, 5, 5, 5, 5, 5, 5, 5, 3, 3, 5, 5, 5, 5, 5, 5, 5, 5, 5, 5, 6, 5, 2, 5, 5, 5, 3, 5, 5, 5, 5, 5, 5, 3, 3, 3, 3, 3, 3, 3, 3, 3, 3, 3, 3, 3, 3, 2, 3, 3, 3, 3, 3, 3, 3, 3, 3, 3, 3],
         "height":25,
         "name":"BackgroundLayer",
         "opacity":1,
         "type":"tilelayer",
         "visible":true,
         "width":25,
         "x":0,
         "y":0
        }, 
        {
         "data":[2, 2, 2, 2, 2, 2, 2, 2, 2, 2, 2, 2, 2, 2, 2, 2, 2, 2, 2, 2, 2, 2, 2, 2, 2, 2, 0, 0, 0, 0, 0, 2, 0, 0, 0, 0, 0, 0, 0, 0, 2, 0, 0, 0, 0, 0, 0, 0, 0, 2, 2, 0, 0, 0, 0, 0, 2, 0, 0, 0, 0, 0, 0, 0, 0, 2, 0, 0, 0, 0, 0, 0, 0, 0, 2, 2, 2, 2, 2, 2, 2, 2, 0, 0, 0, 0, 0, 0, 0, 0, 2, 0, 0, 0, 0, 0, 0, 0, 0, 2, 2, 0, 0, 0, 0, 0, 2, 0, 0, 0, 0, 0, 0, 0, 0, 2, 0, 0, 0, 0, 0, 0, 0, 0, 2, 2, 0, 0, 0, 0, 0, 2, 0, 0, 0, 0, 0, 0, 0, 0, 2, 0, 0, 0, 0, 0, 0, 0, 0, 2, 2, 0, 0, 0, 0, 0, 2, 0, 0, 0, 0, 0, 0, 0, 0, 2, 0, 0, 0, 0, 0, 0, 0, 0, 2, 2, 0, 0, 0, 0, 0, 2, 0, 0, 0, 0, 0, 0, 0, 0, 2, 0, 0, 0, 0, 0, 0, 0, 0, 2, 2, 0, 0, 0, 0, 0, 2, 0, 0, 0, 0, 0, 0, 0, 0, 2, 0, 0, 0, 0, 0, 0, 0, 0, 2, 2, 0, 0, 0, 0, 0, 2, 0, 0, 0, 0, 0, 0, 0, 0, 2, 0, 0, 0, 0, 0, 0, 0, 0, 2, 2, 0, 0, 0, 0, 0, 2, 0, 0, 0, 0, 0, 0, 0, 0, 2, 0, 0, 0, 0, 0, 0, 0, 0, 2, 2, 0, 0, 0, 0, 0, 2, 0, 0, 0, 0, 0, 0, 0, 0, 2, 0, 0, 0, 0, 0, 0, 0, 0, 2, 2, 0, 0, 0, 0, 0, 2, 0, 0, 0, 0, 0, 0, 0, 0, 2, 0, 0, 0, 0, 0, 0, 0, 0, 2, 2, 2, 2, 2, 2, 2, 2, 2, 2, 2, 2, 2, 2, 2, 2, 2, 2, 2, 2, 2, 2, 2, 2, 2, 2, 2, 0, 0, 0, 0, 0, 0, 0, 0, 0, 0, 0, 0, 2, 0, 0, 0, 0, 0, 0, 2, 0, 0, 0, 2, 2, 0, 0, 0, 0, 0, 0, 0, 0, 0, 0, 0, 0, 2, 0, 0, 0, 0, 0, 0, 0, 0, 0, 0, 2, 2, 0, 0, 0, 0, 0, 0, 0, 0, 0, 0, 0, 0, 2, 0, 0, 0, 0, 2, 0, 0, 0, 0, 0, 2, 2, 0, 0, 0, 0, 0, 0, 0, 0, 0, 0, 0, 0, 2, 0, 0, 0, 0, 0, 0, 0, 0, 0, 2, 2, 2, 0, 0, 0, 0, 0, 0, 0, 0, 0, 0, 0, 0, 2, 0, 0, 2, 0, 0, 0, 0, 0, 0, 0, 2, 2, 0, 0, 0, 0, 0, 0, 0, 0, 0, 0, 0, 0, 2, 0, 0, 0, 0, 0, 0, 0, 2, 0, 0, 2, 2, 0, 0, 0, 0, 0, 0, 0, 0, 0, 0, 0, 0, 2, 2, 0, 0, 0, 0, 0, 0, 0, 0, 0, 2, 2, 0, 0, 0, 0, 0, 0, 0, 0, 0, 0, 0, 0, 2, 0, 0, 0, 0, 0, 2, 0, 0, 0, 0, 2, 2, 0, 0, 0, 0, 0, 0, 0, 0, 0, 0, 0, 0, 2, 0, 0, 0, 0, 0, 0, 0, 0, 0, 0, 2, 2, 0, 0, 0, 0, 0, 0, 0, 0, 0, 0, 0, 0, 2, 0, 0, 0, 2, 0, 0, 0, 0, 0, 0, 2, 2, 2, 2, 2, 2, 2, 2, 2, 2, 2, 2, 2, 2, 2, 2, 2, 2, 2, 2, 2, 2, 2, 2, 2, 2],
         "height":25,
         "name":"BlockedLayer",
         "opacity":1,
         "type":"tilelayer",
         "visible":true,
         "width":25,
         "x":0,
         "y":0
        }, 
        {
         "draworder":"topdown",
         "height":0,
         "name":"ObjectLayer",
         "objects":[
                {
                 "gid":6,
                 "height":128,
                 "id":4,
                 "name":"",
                 "properties":
                    {
                     "Teleporter":"1"
                    },
                 "propertytypes":
                    {
                     "Teleporter":"string"
                    },
                 "rotation":0,
                 "type":"",
                 "visible":true,
                 "width":128,
                 "x":512,
                 "y":256
                }, 
                {
                 "gid":6,
                 "height":128,
                 "id":5,
                 "name":"",
                 "properties":
                    {
                     "Teleporter":"2"
                    },
                 "propertytypes":
                    {
                     "Teleporter":"string"
                    },
                 "rotation":0,
                 "type":"",
                 "visible":true,
                 "width":128,
                 "x":384,
                 "y":1532
                }, 
                {
                 "gid":6,
                 "height":128,
                 "id":6,
                 "name":"",
                 "properties":
                    {
                     "Teleporter":"1"
                    },
                 "propertytypes":
                    {
                     "Teleporter":"string"
                    },
                 "rotation":0,
                 "type":"",
                 "visible":true,
                 "width":128,
                 "x":128,
                 "y":640
                }, 
                {
                 "gid":6,
                 "height":128,
                 "id":7,
                 "name":"",
                 "properties":
                    {
                     "Teleporter":"2"
                    },
                 "propertytypes":
                    {
                     "Teleporter":"string"
                    },
                 "rotation":0,
                 "type":"",
                 "visible":true,
                 "width":128,
                 "x":896,
                 "y":256
                }, 
                {
                 "gid":6,
                 "height":128,
                 "id":8,
                 "name":"",
                 "properties":
                    {
                     "Teleporter":"3"
                    },
                 "propertytypes":
                    {
                     "Teleporter":"string"
                    },
                 "rotation":0,
                 "type":"",
                 "visible":true,
                 "width":128,
                 "x":1668,
                 "y":256
                }, 
                {
                 "gid":6,
                 "height":128,
                 "id":9,
                 "name":"",
                 "properties":
                    {
                     "Teleporter":"3"
                    },
                 "propertytypes":
                    {
                     "Teleporter":"string"
                    },
                 "rotation":0,
                 "type":"",
                 "visible":true,
                 "width":128,
                 "x":2048,
                 "y":1660
                }, 
                {
                 "gid":6,
                 "height":128,
                 "id":10,
                 "name":"",
                 "properties":
                    {
                     "Teleporter":"4"
                    },
                 "propertytypes":
                    {
                     "Teleporter":"string"
                    },
                 "rotation":0,
                 "type":"",
                 "visible":true,
                 "width":128,
                 "x":2820,
                 "y":256
                }, 
                {
                 "gid":6,
                 "height":128,
                 "id":11,
                 "name":"",
                 "properties":
                    {
                     "Teleporter":"4"
                    },
                 "propertytypes":
                    {
                     "Teleporter":"string"
                    },
                 "rotation":0,
                 "type":"",
                 "visible":true,
                 "width":128,
                 "x":772,
                 "y":2420
                }, 
                {
                 "gid":6,
                 "height":128,
                 "id":12,
                 "name":"",
                 "properties":
                    {
                     "Teleporter":"5"
                    },
                 "propertytypes":
                    {
                     "Teleporter":"string"
                    },
                 "rotation":0,
                 "type":"",
                 "visible":true,
                 "width":128,
                 "x":1404,
                 "y":3064
                }, 
                {
                 "gid":6,
                 "height":128,
                 "id":13,
                 "name":"",
                 "properties":
                    {
                     "Teleporter":"5"
                    },
                 "propertytypes":
                    {
                     "Teleporter":"string"
                    },
                 "rotation":0,
                 "type":"",
                 "visible":true,
                 "width":128,
                 "x":1792,
                 "y":1920
                }],
         "opacity":1,
         "type":"objectgroup",
         "visible":false,
         "width":0,
         "x":0,
         "y":0
        }],
 "nextobjectid":14,
 "orientation":"orthogonal",
 "renderorder":"right-down",
 "tileheight":128,
 "tilesets":[
        {
         "columns":5,
         "firstgid":1,
         "image":"tilesheet.png",
         "imageheight":640,
         "imagewidth":640,
         "margin":0,
         "name":"tilesheet",
         "spacing":0,
         "tilecount":25,
         "tileheight":128,
         "tilewidth":128
        }],
 "tilewidth":128,
 "version":1,
 "width":25
}